{
  "id": "99708de4-cdcd-4b80-b7d5-bead7e3ea049",
  "prevId": "4bb0d889-b87d-4783-90bb-a95d34ec1d92",
  "version": "7",
  "dialect": "postgresql",
  "tables": {
    "public.patients": {
      "name": "patients",
      "schema": "",
      "columns": {
        "id": {
          "name": "id",
          "type": "uuid",
          "primaryKey": true,
          "notNull": true,
          "default": "gen_random_uuid()"
        },
        "nom": {
          "name": "nom",
          "type": "varchar(100)",
          "primaryKey": false,
          "notNull": true
        },
        "prenom": {
          "name": "prenom",
          "type": "varchar(100)",
          "primaryKey": false,
          "notNull": true
        },
        "date_naissance": {
          "name": "date_naissance",
          "type": "date",
          "primaryKey": false,
          "notNull": false
        },
        "type_avc": {
          "name": "type_avc",
          "type": "varchar(100)",
          "primaryKey": false,
          "notNull": false
        },
        "zone_atteinte": {
          "name": "zone_atteinte",
          "type": "varchar(255)",
          "primaryKey": false,
          "notNull": false
        },
        "created_by": {
          "name": "created_by",
          "type": "uuid",
          "primaryKey": false,
          "notNull": false
        },
        "created_at": {
          "name": "created_at",
          "type": "timestamp",
          "primaryKey": false,
          "notNull": true,
          "default": "now()"
        }
      },
      "indexes": {},
      "foreignKeys": {
        "patients_created_by_users_id_fk": {
          "name": "patients_created_by_users_id_fk",
          "tableFrom": "patients",
          "tableTo": "users",
          "columnsFrom": [
            "created_by"
          ],
          "columnsTo": [
            "id"
          ],
          "onDelete": "no action",
          "onUpdate": "no action"
        }
      },
      "compositePrimaryKeys": {},
      "uniqueConstraints": {},
      "policies": {},
      "checkConstraints": {},
      "isRLSEnabled": false
    },
    "public.scores": {
      "name": "scores",
      "schema": "",
      "columns": {
        "id": {
          "name": "id",
          "type": "uuid",
          "primaryKey": true,
          "notNull": true,
          "default": "gen_random_uuid()"
        },
        "patient_id": {
          "name": "patient_id",
          "type": "uuid",
          "primaryKey": false,
          "notNull": true
        },
        "exercice": {
          "name": "exercice",
          "type": "varchar(100)",
          "primaryKey": false,
          "notNull": true
        },
        "domaine": {
          "name": "domaine",
          "type": "varchar(100)",
          "primaryKey": false,
          "notNull": true
        },
        "score": {
          "name": "score",
          "type": "integer",
          "primaryKey": false,
          "notNull": true
        },
        "niveau_difficulte": {
          "name": "niveau_difficulte",
          "type": "difficulte",
          "typeSchema": "public",
          "primaryKey": false,
          "notNull": true
        },
        "date": {
          "name": "date",
          "type": "timestamp",
          "primaryKey": false,
          "notNull": true,
          "default": "now()"
        }
      },
      "indexes": {},
      "foreignKeys": {
        "scores_patient_id_patients_id_fk": {
          "name": "scores_patient_id_patients_id_fk",
          "tableFrom": "scores",
          "tableTo": "patients",
          "columnsFrom": [
            "patient_id"
          ],
          "columnsTo": [
            "id"
          ],
          "onDelete": "cascade",
          "onUpdate": "no action"
        }
      },
      "compositePrimaryKeys": {},
      "uniqueConstraints": {},
      "policies": {},
      "checkConstraints": {},
      "isRLSEnabled": false
    },
    "public.seances": {
      "name": "seances",
      "schema": "",
      "columns": {
        "id": {
          "name": "id",
          "type": "uuid",
          "primaryKey": true,
          "notNull": true,
          "default": "gen_random_uuid()"
        },
        "patient_id": {
          "name": "patient_id",
          "type": "uuid",
          "primaryKey": false,
          "notNull": true
        },
        "fatigue": {
          "name": "fatigue",
          "type": "fatigue",
          "typeSchema": "public",
          "primaryKey": false,
          "notNull": true
        },
        "a_douleur": {
          "name": "a_douleur",
          "type": "boolean",
          "primaryKey": false,
          "notNull": true
        },
        "eva_douleur": {
          "name": "eva_douleur",
          "type": "integer",
          "primaryKey": false,
          "notNull": false
        },
        "created_at": {
          "name": "created_at",
          "type": "timestamp",
          "primaryKey": false,
          "notNull": true,
          "default": "now()"
        }
      },
      "indexes": {},
      "foreignKeys": {
        "seances_patient_id_patients_id_fk": {
          "name": "seances_patient_id_patients_id_fk",
          "tableFrom": "seances",
          "tableTo": "patients",
          "columnsFrom": [
            "patient_id"
          ],
          "columnsTo": [
            "id"
          ],
          "onDelete": "cascade",
          "onUpdate": "no action"
        }
      },
      "compositePrimaryKeys": {},
      "uniqueConstraints": {},
      "policies": {},
      "checkConstraints": {},
      "isRLSEnabled": false
    },
    "public.users": {
      "name": "users",
      "schema": "",
      "columns": {
        "id": {
          "name": "id",
          "type": "uuid",
          "primaryKey": true,
          "notNull": true,
          "default": "gen_random_uuid()"
        },
        "name": {
          "name": "name",
          "type": "varchar(100)",
          "primaryKey": false,
          "notNull": true
        },
        "email": {
          "name": "email",
          "type": "varchar(255)",
          "primaryKey": false,
          "notNull": true
        },
        "password": {
          "name": "password",
          "type": "varchar(255)",
          "primaryKey": false,
          "notNull": true
        },
        "role": {
          "name": "role",
          "type": "role",
          "typeSchema": "public",
          "primaryKey": false,
          "notNull": true,
          "default": "'therapeute'"
        },
        "created_at": {
          "name": "created_at",
          "type": "timestamp",
          "primaryKey": false,
          "notNull": true,
          "default": "now()"
        }
      },
      "indexes": {},
      "foreignKeys": {},
      "compositePrimaryKeys": {},
      "uniqueConstraints": {
        "users_email_unique": {
          "name": "users_email_unique",
          "nullsNotDistinct": false,
          "columns": [
            "email"
          ]
        }
      },
      "policies": {},
      "checkConstraints": {},
      "isRLSEnabled": false
    }
  },
  "enums": {
    "public.difficulte": {
      "name": "difficulte",
      "schema": "public",
      "values": [
        "facile",
        "moyen",
        "difficile"
      ]
    },
    "public.fatigue": {
      "name": "fatigue",
      "schema": "public",
      "values": [
        "pas_du_tout",
        "un_peu",
        "moyennement"
      ]
    },
    "public.role": {
      "name": "role",
      "schema": "public",
      "values": [
        "admin",
        "therapeute"
      ]
    }
  },
  "schemas": {},
  "sequences": {},
  "roles": {},
  "policies": {},
  "views": {},
  "_meta": {
    "columns": {},
    "schemas": {},
    "tables": {}
  }
}